MANIFEST.in
README.md
gpio.py
setup.cfg
setup.py
gpio.egg-info/PKG-INFO
gpio.egg-info/SOURCES.txt
gpio.egg-info/dependency_links.txt
gpio.egg-info/pbr.json
gpio.egg-info/top_level.txt