Metadata-Version: 1.1
Name: gpio
Version: 0.1.1
Summary: gpio access via the standard linux sysfs interface
Home-page: https://github.com/cloudformdesign/gpio
Author: Garrett Berg
Author-email: garrett@cloudformdesign.com
License: MIT
Platform: UNKNOWN
Classifier: Intended Audience :: Developers
Classifier: License :: OSI Approved :: MIT License
Classifier: Operating System :: POSIX
Classifier: Programming Language :: Python :: 2.7
Classifier: Programming Language :: Python :: 3
Classifier: Topic :: Software Development :: Embedded Systems
Classifier: Topic :: Software Development :: Libraries :: Python Modules
